roapipy/__init__.py
roapipy/roapipy.py
roapipy-1.0.0.dist-info/LICENSE.txt
roapipy-1.0.0.dist-info/METADATA
roapipy-1.0.0.dist-info/WHEEL
roapipy-1.0.0.dist-info/top_level.txt
roapipy-1.0.0.dist-info/RECORD
