Metadata-Version: 2.1
Name: roapipy
Version: 1.0.0
Summary: roapipy - A wrapper for the Roblox API built for Python
Author: Gytis
Maintainer: Gytis
Project-URL: Developer, https://discord.com/users/301014178703998987
Classifier: Programming Language :: Python :: 3
Classifier: License :: OSI Approved :: MIT License
Classifier: Operating System :: OS Independent
Requires-Python: >=3.8
License-File: LICENSE.txt
